Workbook

Sheet Summary
A1: Olist e-commerce: executive KPIs (Jan 2017 - Aug 2018)
A2: Every value below is a formula over the data sheets. Source: Olist public dataset (Kaggle), real data.
A4: KPI | B4: Value
A5: Revenue (item prices, R$) | B5: =SUM(Monthly!B5:B24) -> 13449530
A6: Orders | B6: =SUM(Monthly!C5:C24) -> 97905
A7: Average order value (R$) | B7: =B5/B6 -> 137.37327
A8: Customers | B8: =SUM(RFM!B5:B11) -> 94703
A9: Repeat purchase rate | B9: =SUMIF(RFM!G5:G11,"Yes",RFM!B5:B11)/B8 -> 0.030347507
A10: On-time delivery rate | B10: =1-SUM(Region!E5:E31)/SUM(Region!D5:D31) -> 0.9321123
A11: Average delivery days | B11: =SUM(Region!F5:F31)/SUM(Region!D5:D31) -> 12.538461
A12: Average review score | B12: =SUM(Region!G5:G31)/SUM(Region!H5:H31) -> 4.1173208
A13: Jan-Aug YoY revenue growth | B13: =SUM(Monthly!B17:B24)/SUM(Monthly!B5:B12)-1 -> 1.3827955
A14: Top-10 category revenue share | B14: =SUMIF(Category!F5:F78,"<=10",Category!E5:E78) -> 0.62409483
A15: Growth actions: total annual impact (R$) | B15: ='Impact model'!B20 -> 274690.24
A17: Sheets: Monthly, Category, Region, RFM, Payments, Impact model. Rates and averages are recomputed from sums, never typed in.

Sheet Monthly
A1: Monthly KPIs
A2: Values: revenue, orders, customers from the cleaned order table. Columns F-I are formulas.
A4: Month | B4: Revenue | C4: Orders | D4: Customers | E4: New customers | F4: AOV | G4: MoM % | H4: YoY % | I4: Running revenue
A5: 2017-01 | B5: 120098.27 | C5: 787 | D5: 753 | E5: 753 | F5: =B5/C5 -> 152.60263 | I5: =SUM($B$5:B5) -> 120098.27
A6: 2017-02 | B6: 244959.35 | C6: 1718 | D6: 1693 | E6: 1690 | F6: =B6/C6 -> 142.58402 | G6: =B6/B5-1 -> 1.0396576 | I6: =SUM($B$5:B6) -> 365057.62
A7: 2017-03 | B7: 368341.32 | C7: 2617 | D7: 2577 | E7: 2571 | F7: =B7/C7 -> 140.74945 | G7: =B7/B6-1 -> 0.50368345 | I7: =SUM($B$5:B7) -> 733398.94
A8: 2017-04 | B8: 353842.98 | C8: 2377 | D8: 2345 | E8: 2326 | F8: =B8/C8 -> 148.86116 | G8: =B8/B7-1 -> -0.039361156 | I8: =SUM($B$5:B8) -> 1087241.9
A9: 2017-05 | B9: 503159.19 | C9: 3640 | D9: 3569 | E9: 3541 | F9: =B9/C9 -> 138.23055 | G9: =B9/B8-1 -> 0.42198438 | I9: =SUM($B$5:B9) -> 1590401.1
A10: 2017-06 | B10: 429916.61 | C10: 3205 | D10: 3142 | E10: 3102 | F10: =B10/C10 -> 134.13935 | G10: =B10/B9-1 -> -0.14556542 | I10: =SUM($B$5:B10) -> 2020317.7
A11: 2017-07 | B11: 492287.3 | C11: 3946 | D11: 3872 | E11: 3823 | F11: =B11/C11 -> 124.75603 | G11: =B11/B10-1 -> 0.14507625 | I11: =SUM($B$5:B11) -> 2512605
A12: 2017-08 | B12: 568245.79 | C12: 4272 | D12: 4191 | E12: 4130 | F12: =B12/C12 -> 133.01634 | G12: =B12/B11-1 -> 0.15429707 | I12: =SUM($B$5:B12) -> 3080850.8
A13: 2017-09 | B13: 621415.91 | C13: 4227 | D13: 4154 | E13: 4076 | F13: =B13/C13 -> 147.0111 | G13: =B13/B12-1 -> 0.093568876 | I13: =SUM($B$5:B13) -> 3702266.7
A14: 2017-10 | B14: 660179.62 | C14: 4547 | D14: 4481 | E14: 4392 | F14: =B14/C14 -> 145.19015 | G14: =B14/B13-1 -> 0.062379655 | I14: =SUM($B$5:B14) -> 4362446.3
A15: 2017-11 | B15: 1003862.1 | C15: 7421 | D15: 7313 | E15: 7189 | F15: =B15/C15 -> 135.27316 | G15: =B15/B14-1 -> 0.52058941 | I15: =SUM($B$5:B15) -> 5366308.5
A16: 2017-12 | B16: 742183.79 | C16: 5618 | D16: 5551 | E16: 5437 | F16: =B16/C16 -> 132.10819 | G16: =B16/B15-1 -> -0.2606716 | I16: =SUM($B$5:B16) -> 6108492.3
A17: 2018-01 | B17: 945456.29 | C17: 7187 | D17: 7088 | E17: 6952 | F17: =B17/C17 -> 131.5509 | G17: =B17/B16-1 -> 0.27388432 | H17: =B17/B5-1 -> 6.8723556 | I17: =SUM($B$5:B17) -> 7053948.6
A18: 2018-02 | B18: 837895.43 | C18: 6624 | D18: 6468 | E18: 6356 | F18: =B18/C18 -> 126.49388 | G18: =B18/B17-1 -> -0.11376608 | H18: =B18/B6-1 -> 2.4205489 | I18: =SUM($B$5:B18) -> 7891844
A19: 2018-03 | B19: 981051.06 | C19: 7168 | D19: 7077 | E19: 6932 | F19: =B19/C19 -> 136.86538 | G19: =B19/B18-1 -> 0.17085143 | H19: =B19/B7-1 -> 1.6634293 | I19: =SUM($B$5:B19) -> 8872895
A20: 2018-04 | B20: 993592.98 | C20: 6919 | D20: 6863 | E20: 6698 | F20: =B20/C20 -> 143.60355 | G20: =B20/B19-1 -> 0.012784166 | H20: =B20/B8-1 -> 1.8080053 | I20: =SUM($B$5:B20) -> 9866488
A21: 2018-05 | B21: 992871.75 | C21: 6833 | D21: 6775 | E21: 6588 | F21: =B21/C21 -> 145.30539 | G21: =B21/B20-1 -> -0.00072588073 | H21: =B21/B9-1 -> 0.97327559 | I21: =SUM($B$5:B21) -> 10859360
A22: 2018-06 | B22: 863265.53 | C22: 6145 | D22: 6106 | E22: 5921 | F22: =B22/C22 -> 140.48259 | G22: =B22/B21-1 -> -0.13053672 | H22: =B22/B10-1 -> 1.0079837 | I22: =SUM($B$5:B22) -> 11722625
A23: 2018-07 | B23: 878044.27 | C23: 6233 | D23: 6172 | E23: 6017 | F23: =B23/C23 -> 140.87025 | G23: =B23/B22-1 -> 0.017119576 | H23: =B23/B11-1 -> 0.7836013 | I23: =SUM($B$5:B23) -> 12600670
A24: 2018-08 | B24: 848860.1 | C24: 6421 | D24: 6380 | E24: 6209 | F24: =B24/C24 -> 132.20061 | G24: =B24/B23-1 -> -0.033237698 | H24: =B24/B12-1 -> 0.49382559 | I24: =SUM($B$5:B24) -> 13449530

Sheet Category
A1: Category performance
A2: Values: item revenue, items, freight by category. Share, rank, cumulative share and freight ratio are formulas.
A4: Category | B4: Revenue | C4: Items | D4: Freight | E4: Revenue share | F4: Rank | G4: Cumulative share | H4: Freight / revenue
A5: health_beauty | B5: 1251145.5 | C5: 9585 | D5: 181067.84 | E5: =B5/SUM($B$5:$B$78) -> 0.093025226 | F5: =RANK(B5,$B$5:$B$78) -> 1 | G5: =SUM($B$5:B5)/SUM($B$5:$B$78) -> 0.093025226 | H5: =D5/B5 -> 0.14472164
A6: watches_gifts | B6: 1194825 | C6: 5965 | D6: 99999.46 | E6: =B6/SUM($B$5:$B$78) -> 0.088837677 | F6: =RANK(B6,$B$5:$B$78) -> 2 | G6: =SUM($B$5:B6)/SUM($B$5:$B$78) -> 0.1818629 | H6: =D6/B6 -> 0.083693815
A7: bed_bath_table | B7: 1035485.1 | C7: 11089 | D7: 204294.48 | E7: =B7/SUM($B$5:$B$78) -> 0.07699043 | F7: =RANK(B7,$B$5:$B$78) -> 3 | G7: =SUM($B$5:B7)/SUM($B$5:$B$78) -> 0.25885333 | H7: =D7/B7 -> 0.19729351
A8: sports_leisure | B8: 977728.77 | C8: 8573 | D8: 167025.1 | E8: =B8/SUM($B$5:$B$78) -> 0.072696131 | F8: =RANK(B8,$B$5:$B$78) -> 4 | G8: =SUM($B$5:B8)/SUM($B$5:$B$78) -> 0.33154946 | H8: =D8/B8 -> 0.17082969
A9: computers_accessories | B9: 902922.7 | C9: 7760 | D9: 146278.79 | E9: =B9/SUM($B$5:$B$78) -> 0.067134147 | F9: =RANK(B9,$B$5:$B$78) -> 5 | G9: =SUM($B$5:B9)/SUM($B$5:$B$78) -> 0.39868361 | H9: =D9/B9 -> 0.16200588
A10: furniture_decor | B10: 721584.27 | C10: 8229 | D10: 170853.26 | E10: =B10/SUM($B$5:$B$78) -> 0.053651264 | F10: =RANK(B10,$B$5:$B$78) -> 6 | G10: =SUM($B$5:B10)/SUM($B$5:$B$78) -> 0.45233487 | H10: =D10/B10 -> 0.2367752
A11: housewares | B11: 625538.73 | C11: 6903 | D11: 144953.87 | E11: =B11/SUM($B$5:$B$78) -> 0.046510082 | F11: =RANK(B11,$B$5:$B$78) -> 7 | G11: =SUM($B$5:B11)/SUM($B$5:$B$78) -> 0.49884496 | H11: =D11/B11 -> 0.23172645
A12: cool_stuff | B12: 619724.39 | C12: 3772 | D12: 83124.97 | E12: =B12/SUM($B$5:$B$78) -> 0.046077774 | F12: =RANK(B12,$B$5:$B$78) -> 8 | G12: =SUM($B$5:B12)/SUM($B$5:$B$78) -> 0.54492273 | H12: =D12/B12 -> 0.13413216
A13: auto | B13: 585177.48 | C13: 4195 | D13: 91676.7 | E13: =B13/SUM($B$5:$B$78) -> 0.043509141 | F13: =RANK(B13,$B$5:$B$78) -> 9 | G13: =SUM($B$5:B13)/SUM($B$5:$B$78) -> 0.58843187 | H13: =D13/B13 -> 0.15666478
A14: garden_tools | B14: 479650.06 | C14: 4323 | D14: 98409.95 | E14: =B14/SUM($B$5:$B$78) -> 0.035662962 | F14: =RANK(B14,$B$5:$B$78) -> 10 | G14: =SUM($B$5:B14)/SUM($B$5:$B$78) -> 0.62409483 | H14: =D14/B14 -> 0.20517031
A15: toys | B15: 475702.04 | C15: 4059 | D15: 76489.72 | E15: =B15/SUM($B$5:$B$78) -> 0.035369418 | F15: =RANK(B15,$B$5:$B$78) -> 11 | G15: =SUM($B$5:B15)/SUM($B$5:$B$78) -> 0.65946425 | H15: =D15/B15 -> 0.16079334
A16: baby | B16: 408941.03 | C16: 3032 | D16: 67861.42 | E16: =B16/SUM($B$5:$B$78) -> 0.030405601 | F16: =RANK(B16,$B$5:$B$78) -> 12 | G16: =SUM($B$5:B16)/SUM($B$5:$B$78) -> 0.68986985 | H16: =D16/B16 -> 0.16594427
... A78: security_and_services | B78: 283.29 | C78: 2 | D78: 41.22 | E78: =B78/SUM($B$5:$B$78) -> 2.106319e-05 | F78: =RANK(B78,$B$5:$B$78) -> 74 | G78: =SUM($B$5:B78)/SUM($B$5:$B$78) -> 1 | H78: =D78/B78 -> 0.14550461

Sheet Region
A1: Logistics and reviews by customer state
A2: Values: order, delivery and review sums by state. Rates and averages are formulas; F2 holds the national late rate. | E2: National late rate: | F2: =SUM(E5:E31)/SUM(D5:D31) -> 0.067887696
A4: State | B4: Orders | C4: Revenue | D4: Delivered | E4: Late | F4: Delivery-day sum | G4: Review sum | H4: Reviews | I4: Late rate | J4: Avg delivery days | K4: Avg review | L4: vs national
A5: SP | B5: 41021 | C5: 5150778.7 | D5: 40399 | E5: 1817 | F5: 352990.09 | G5: 171695 | H5: 40762 | I5: =IF(D5=0,"",E5/D5) -> 0.044976361 | J5: =IF(D5=0,"",F5/D5) -> 8.7375947 | K5: =IF(H5=0,"",G5/H5) -> 4.2121339 | L5: =IF(AND(D5>=300,I5>$F$2),"Above national","")
A6: RJ | B6: 12654 | C6: 1802436.2 | D6: 12310 | E6: 1495 | F6: 188304.21 | G6: 48810 | H6: 12498 | I6: =IF(D6=0,"",E6/D6) -> 0.12144598 | J6: =IF(D6=0,"",F6/D6) -> 15.296849 | K6: =IF(H6=0,"",G6/H6) -> 3.9054249 | L6: =IF(AND(D6>=300,I6>$F$2),"Above national","") -> Above national
A7: MG | B7: 11457 | C7: 1568856 | D7: 11319 | E7: 519 | F7: 135652.88 | G7: 47431 | H7: 11384 | I7: =IF(D7=0,"",E7/D7) -> 0.045852107 | J7: =IF(D7=0,"",F7/D7) -> 11.984529 | K7: =IF(H7=0,"",G7/H7) -> 4.1664617 | L7: =IF(AND(D7>=300,I7>$F$2),"Above national","")
A8: RS | B8: 5395 | C8: 739357.46 | D8: 5327 | E8: 325 | F8: 81442.758 | G8: 22336 | H8: 5375 | I8: =IF(D8=0,"",E8/D8) -> 0.061009949 | J8: =IF(D8=0,"",F8/D8) -> 15.288672 | K8: =IF(H8=0,"",G8/H8) -> 4.1555349 | L8: =IF(AND(D8>=300,I8>$F$2),"Above national","")
A9: PR | B9: 4962 | C9: 674867.55 | D9: 4903 | E9: 199 | F9: 58704.351 | G9: 20791 | H9: 4936 | I9: =IF(D9=0,"",E9/D9) -> 0.040587395 | J9: =IF(D9=0,"",F9/D9) -> 11.973149 | K9: =IF(H9=0,"",G9/H9) -> 4.2121151 | L9: =IF(AND(D9>=300,I9>$F$2),"Above national","")
A10: SC | B10: 3590 | C10: 516340.22 | D10: 3537 | E10: 291 | F10: 52864.497 | G10: 14604 | H10: 3562 | I10: =IF(D10=0,"",E10/D10) -> 0.082273113 | J10: =IF(D10=0,"",F10/D10) -> 14.94614 | K10: =IF(H10=0,"",G10/H10) -> 4.0999439 | L10: =IF(AND(D10>=300,I10>$F$2),"Above national","") -> Above national
A11: BA | B11: 3340 | C11: 506214.78 | D11: 3253 | E11: 396 | F11: 62893.937 | G11: 12822 | H11: 3301 | I11: =IF(D11=0,"",E11/D11) -> 0.12173378 | J11: =IF(D11=0,"",F11/D11) -> 19.334134 | K11: =IF(H11=0,"",G11/H11) -> 3.8842775 | L11: =IF(AND(D11>=300,I11>$F$2),"Above national","") -> Above national
A12: DF | B12: 2114 | C12: 299842.68 | D12: 2074 | E12: 118 | F12: 26834.598 | G12: 8604 | H12: 2104 | I12: =IF(D12=0,"",E12/D12) -> 0.056894889 | J12: =IF(D12=0,"",F12/D12) -> 12.938572 | K12: =IF(H12=0,"",G12/H12) -> 4.0893536 | L12: =IF(AND(D12>=300,I12>$F$2),"Above national","")
A13: ES | B13: 2014 | C13: 272614.34 | D13: 1992 | E13: 214 | F13: 31425.265 | G13: 8056 | H13: 1987 | I13: =IF(D13=0,"",E13/D13) -> 0.10742972 | J13: =IF(D13=0,"",F13/D13) -> 15.775736 | K13: =IF(H13=0,"",G13/H13) -> 4.0543533 | L13: =IF(AND(D13>=300,I13>$F$2),"Above national","") -> Above national
A14: GO | B14: 1990 | C14: 286886.07 | D14: 1950 | E14: 128 | F14: 30442.644 | G14: 8044 | H14: 1977 | I14: =IF(D14=0,"",E14/D14) -> 0.065641026 | J14: =IF(D14=0,"",F14/D14) -> 15.611612 | K14: =IF(H14=0,"",G14/H14) -> 4.0687911 | L14: =IF(AND(D14>=300,I14>$F$2),"Above national","")
A15: PE | B15: 1636 | C15: 260370.84 | D15: 1587 | E15: 153 | F15: 29279.954 | G15: 6509 | H15: 1619 | I15: =IF(D15=0,"",E15/D15) -> 0.096408318 | J15: =IF(D15=0,"",F15/D15) -> 18.449877 | K15: =IF(H15=0,"",G15/H15) -> 4.020383 | L15: =IF(AND(D15>=300,I15>$F$2),"Above national","") -> Above national
A16: CE | B16: 1316 | C16: 224574.68 | D16: 1273 | E16: 176 | F16: 27036.558 | G16: 5067 | H16: 1307 | I16: =IF(D16=0,"",E16/D16) -> 0.13825609 | J16: =IF(D16=0,"",F16/D16) -> 21.238458 | K16: =IF(H16=0,"",G16/H16) -> 3.8768171 | L16: =IF(AND(D16>=300,I16>$F$2),"Above national","") -> Above national
... A31: RR | B31: 43 | C31: 7626.85 | D31: 40 | E31: 5 | F31: 1196.3063 | G31: 159 | H31: 43 | I31: =IF(D31=0,"",E31/D31) -> 0.125 | J31: =IF(D31=0,"",F31/D31) -> 29.907657 | K31: =IF(H31=0,"",G31/H31) -> 3.6976744 | L31: =IF(AND(D31>=300,I31>$F$2),"Above national","")

Sheet RFM
A1: RFM segments
A2: Values: customers and revenue per segment. Shares and averages are formulas.
A4: Segment | B4: Customers | C4: Revenue | D4: Customer share | E4: Revenue share | F4: Revenue per customer | G4: Repeat buyers?
A5: Promising | B5: 14682 | C5: 3934361.3 | D5: =B5/SUM($B$5:$B$11) -> 0.15503205 | E5: =C5/SUM($C$5:$C$11) -> 0.29252779 | F5: =C5/B5 -> 267.97176 | G5: No
A6: At-Risk | B6: 14097 | C6: 3723194 | D6: =B6/SUM($B$5:$B$11) -> 0.14885484 | E6: =C6/SUM($C$5:$C$11) -> 0.27682707 | F6: =C6/B6 -> 264.11251 | G6: No
A7: Lost | B7: 18487 | C7: 2560725.6 | D7: =B7/SUM($B$5:$B$11) -> 0.19521029 | E7: =C7/SUM($C$5:$C$11) -> 0.19039518 | F7: =C7/B7 -> 138.51494 | G7: No
A8: Hibernating | B8: 22590 | C8: 1262090.5 | D8: =B8/SUM($B$5:$B$11) -> 0.23853521 | E8: =C8/SUM($C$5:$C$11) -> 0.093839006 | F8: =C8/B8 -> 55.869434 | G8: No
A9: New Customers | B9: 21973 | C9: 1222033.5 | D9: =B9/SUM($B$5:$B$11) -> 0.2320201 | E9: =C9/SUM($C$5:$C$11) -> 0.090860682 | F9: =C9/B9 -> 55.615231 | G9: No
A10: Loyal | B10: 1649 | C10: 416297 | D10: =B10/SUM($B$5:$B$11) -> 0.017412331 | E10: =C10/SUM($C$5:$C$11) -> 0.030952532 | F10: =C10/B10 -> 252.45421 | G10: Yes
A11: Champions | B11: 1225 | C11: 330828 | D11: =B11/SUM($B$5:$B$11) -> 0.012935176 | E11: =C11/SUM($C$5:$C$11) -> 0.024597737 | F11: =C11/B11 -> 270.06367 | G11: Yes

Sheet Payments
A1: Payment mix
A2: Values: orders and revenue by primary payment type. Share and AOV are formulas.
A4: Payment type | B4: Orders | C4: Revenue | D4: Order share | E4: AOV
A5: credit_card | B5: 73888 | C5: 10611370 | D5: =B5/SUM($B$5:$B$8) -> 0.75469077 | E5: =C5/B5 -> 143.61426
A6: boleto | B6: 19477 | C6: 2369919.1 | D6: =B6/SUM($B$5:$B$8) -> 0.19893775 | E6: =C6/B6 -> 121.67783
A7: voucher | B7: 3028 | C7: 287339.61 | D7: =B7/SUM($B$5:$B$8) -> 0.03092794 | E7: =C7/B7 -> 94.894191
A8: debit_card | B8: 1512 | C8: 180900.83 | D8: =B8/SUM($B$5:$B$8) -> 0.015443542 | E8: =C8/B8 -> 119.64341

Sheet Impact model
A1: Growth actions: annual revenue impact
A2: Yellow cells are inputs (change them). Blue cells are base values from the analysis.
A4: Base values
A5: Annual new customers (2018 run-rate) | B5: 77509.4
A6: Average repeat-order revenue (R$) | B6: 122.639
A7: Annual orders (2018 run-rate) | B7: 80295
A8: Average add-on revenue per multi-item order (R$) | B8: 111.27
A9: Late orders avoided per year (target states to national rate) | B9: 1477.28
A10: Repeat-rate gap, on-time vs late first order (pp) | B10: 0.5216
A11: Annualised 2018 revenue (R$) | B11: 11011556
A12: Assumptions
A13: Repeat-rate lift from second-purchase programme (pp) | B13: 1
A14: Multi-item order share lift from cross-sell (pp) | B14: 2
A16: Results
A17: A1 Second-purchase programme (R$/yr) | B17: =B5*B13/100*B6 -> 95056.753
A18: A2 Delivery fix in high-late states (R$/yr, via repeat rate) | B18: =B9*B10/100*B6 -> 944.99389
A19: A3 Cross-sell to build baskets (R$/yr) | B19: =B7*B14/100*B8 -> 178688.49
A20: Total (R$/yr) | B20: =SUM(B17:B19) -> 274690.24
A21: Total as % of annualised 2018 revenue | B21: =B20/B11 -> 0.024945633
A24: Sensitivity: A1 revenue by repeat-rate lift
A25: Repeat-rate lift (pp) | B25: A1 revenue (R$/yr)
A26: 0.5 | B26: =$B$5*A26/100*$B$6 -> 47528.377
A27: 1 | B27: =$B$5*A27/100*$B$6 -> 95056.753
A28: 1.5 | B28: =$B$5*A28/100*$B$6 -> 142585.13
A29: 2 | B29: =$B$5*A29/100*$B$6 -> 190113.51
A30: 2.5 | B30: =$B$5*A30/100*$B$6 -> 237641.88
A31: 3 | B31: =$B$5*A31/100*$B$6 -> 285170.26
